Workbook

Sheet Read me
A1: Sawa rate card
A3: What this is
A4: Schedule 2 of the Operator Supply Agreement and Schedule 1 of the Agency Reseller Agreement. One row per product.
A6: How to fill it in
A7: Yellow cells with blue text are inputs. Everything else is calculated: don't overwrite it.
A8: Amounts are in the currency set on the Assumptions sheet.
A9: The first row on each product sheet (shaded, marked EXAMPLE) uses illustrative numbers to show the formulas working. Delete or overwrite it once real rows are filled.
A11: How operators are paid
A12: Day tours and one-way road tours: a departure fee by group size (4–6, 7–9, 10–12 travellers) plus a per-traveller amount (tickets, meals, other per-person costs).
A13: Cruises and multi-day tours: per-traveller land services, per-room amounts by occupancy for the whole trip, and a departure fee by group size for guide and transport.
A15: What the checks show
A16: Sawa margin columns show what Sawa keeps in three scenarios, after operator costs, agency commission and payment fees.
... A22: Title fix: #13 should read "Temples of Ramesses II & Nefertari".

Sheet Assumptions
A1: Assumptions
A3: Assumption | B3: Value | C3: Note
A4: Currency | B4: USD | C4: Replace with the currency you agree with operators (clause 9.4).
A5: Payment processing fee (% of retail) | B5: 0.03 | C5: Placeholder. Replace with your payment provider's actual rate.
A6: Scenario B: direct seats | B6: 5 | C6: Of 8 travellers
A7: Scenario B: agency seats | B7: 3 | C7: Of 8 travellers
A8: Scenario C: direct seats | B8: 6 | C8: Of 12 travellers
A9: Scenario C: agency seats | B9: 6 | C9: Of 12 travellers

Sheet Day tours
A1: Day tours and one-way road tours
A3: # | B3: Product | C3: Type | D3: Base | E3: Frequency | F3: Retail price per seat | G3: Per-traveller amount | H3: Departure fee 4–6 | I3: Departure fee 7–9 | J3: Departure fee 10–12 | K3: Agency commission per seat | L3: Sawa margin A: 4 direct | M3: Sawa margin B: 8 (5 direct, 3 agency) | N3: Sawa margin C: 12 (6 direct, 6 agency) | O3: Loss at 4? | P3: Notes
A4: EX | B4: EXAMPLE (illustrative numbers) | C4: Day tour | D4: Aswan | E4: Daily | F4: 95 | G4: 40 | H4: 150 | I4: 200 | J4: 250 | K4: 12 | L4: =IF(F4="","",4*F4-(4*G4+H4)-4*F4*Assumptions!$B$5) -> 58.6 | M4: =IF(F4="","",(Assumptions!$B$6+Assumptions!$B$7)*F4-((Assumptions!$B$6+Assumptions!$B$7)*G4+I4)-Assumptions!$B$7*K4-(Assumptions!$B$6+Assumptions!$B$7)*F4*Assumptions!$B$5) -> 181.2 | N4: =IF(F4="","",(Assumptions!$B$8+Assumptions!$B$9)*F4-((Assumptions!$B$8+Assumptions!$B$9)*G4+J4)-Assumptions!$B$9*K4-(Assumptions!$B$8+Assumptions!$B$9)*F4*Assumptions!$B$5) -> 303.8 | O4: =IF(L4="","",IF(L4<0,"LOSS","OK")) -> OK | P4: Illustrative only; not a real rate
A5: 1 | B5: Giza Pyramids, Sphinx & the Grand Egyptian Museum | C5: Day tour | D5: Cairo | E5: Daily | L5: =IF(F5="","",4*F5-(4*G5+H5)-4*F5*Assumptions!$B$5) | M5: =IF(F5="","",(Assumptions!$B$6+Assumptions!$B$7)*F5-((Assumptions!$B$6+Assumptions!$B$7)*G5+I5)-Assumptions!$B$7*K5-(Assumptions!$B$6+Assumptions!$B$7)*F5*Assumptions!$B$5) | N5: =IF(F5="","",(Assumptions!$B$8+Assumptions!$B$9)*F5-((Assumptions!$B$8+Assumptions!$B$9)*G5+J5)-Assumptions!$B$9*K5-(Assumptions!$B$8+Assumptions!$B$9)*F5*Assumptions!$B$5) | O5: =IF(L5="","",IF(L5<0,"LOSS","OK"))
A6: 2 | B6: Giza Uncovered: Pyramids, Sphinx & Stories | C6: Day tour | D6: Cairo | E6: Review | L6: =IF(F6="","",4*F6-(4*G6+H6)-4*F6*Assumptions!$B$5) | M6: =IF(F6="","",(Assumptions!$B$6+Assumptions!$B$7)*F6-((Assumptions!$B$6+Assumptions!$B$7)*G6+I6)-Assumptions!$B$7*K6-(Assumptions!$B$6+Assumptions!$B$7)*F6*Assumptions!$B$5) | N6: =IF(F6="","",(Assumptions!$B$8+Assumptions!$B$9)*F6-((Assumptions!$B$8+Assumptions!$B$9)*G6+J6)-Assumptions!$B$9*K6-(Assumptions!$B$8+Assumptions!$B$9)*F6*Assumptions!$B$5) | O6: =IF(L6="","",IF(L6<0,"LOSS","OK")) | P6: Competes with #1
A7: 3 | B7: Secrets of the Grand Egyptian Museum | C7: Day tour | D7: Cairo | E7: Review | L7: =IF(F7="","",4*F7-(4*G7+H7)-4*F7*Assumptions!$B$5) | M7: =IF(F7="","",(Assumptions!$B$6+Assumptions!$B$7)*F7-((Assumptions!$B$6+Assumptions!$B$7)*G7+I7)-Assumptions!$B$7*K7-(Assumptions!$B$6+Assumptions!$B$7)*F7*Assumptions!$B$5) | N7: =IF(F7="","",(Assumptions!$B$8+Assumptions!$B$9)*F7-((Assumptions!$B$8+Assumptions!$B$9)*G7+J7)-Assumptions!$B$9*K7-(Assumptions!$B$8+Assumptions!$B$9)*F7*Assumptions!$B$5) | O7: =IF(L7="","",IF(L7<0,"LOSS","OK")) | P7: Competes with #1
A8: 4 | B8: Memphis, Saqqara & Dahshur: Birth of the Pyramid | C8: Day tour | D8: Cairo | E8: 3x weekly | L8: =IF(F8="","",4*F8-(4*G8+H8)-4*F8*Assumptions!$B$5) | M8: =IF(F8="","",(Assumptions!$B$6+Assumptions!$B$7)*F8-((Assumptions!$B$6+Assumptions!$B$7)*G8+I8)-Assumptions!$B$7*K8-(Assumptions!$B$6+Assumptions!$B$7)*F8*Assumptions!$B$5) | N8: =IF(F8="","",(Assumptions!$B$8+Assumptions!$B$9)*F8-((Assumptions!$B$8+Assumptions!$B$9)*G8+J8)-Assumptions!$B$9*K8-(Assumptions!$B$8+Assumptions!$B$9)*F8*Assumptions!$B$5) | O8: =IF(L8="","",IF(L8<0,"LOSS","OK"))
A9: 5 | B9: Cairo to Alexandria: the Mediterranean Day Tour | C9: Day tour | D9: Cairo | E9: 2x weekly | L9: =IF(F9="","",4*F9-(4*G9+H9)-4*F9*Assumptions!$B$5) | M9: =IF(F9="","",(Assumptions!$B$6+Assumptions!$B$7)*F9-((Assumptions!$B$6+Assumptions!$B$7)*G9+I9)-Assumptions!$B$7*K9-(Assumptions!$B$6+Assumptions!$B$7)*F9*Assumptions!$B$5) | N9: =IF(F9="","",(Assumptions!$B$8+Assumptions!$B$9)*F9-((Assumptions!$B$8+Assumptions!$B$9)*G9+J9)-Assumptions!$B$9*K9-(Assumptions!$B$8+Assumptions!$B$9)*F9*Assumptions!$B$5) | O9: =IF(L9="","",IF(L9<0,"LOSS","OK"))
A10: 6 | B10: Fayoum Oasis, Meidum & Hawara Pyramids | C10: Day tour | D10: Cairo | E10: Weekly | L10: =IF(F10="","",4*F10-(4*G10+H10)-4*F10*Assumptions!$B$5) | M10: =IF(F10="","",(Assumptions!$B$6+Assumptions!$B$7)*F10-((Assumptions!$B$6+Assumptions!$B$7)*G10+I10)-Assumptions!$B$7*K10-(Assumptions!$B$6+Assumptions!$B$7)*F10*Assumptions!$B$5) | N10: =IF(F10="","",(Assumptions!$B$8+Assumptions!$B$9)*F10-((Assumptions!$B$8+Assumptions!$B$9)*G10+J10)-Assumptions!$B$9*K10-(Assumptions!$B$8+Assumptions!$B$9)*F10*Assumptions!$B$5) | O10: =IF(L10="","",IF(L10<0,"LOSS","OK"))
A11: 7 | B11: Whale Valley & Wadi El Rayan: Fayoum Desert Safari | C11: Day tour | D11: Cairo | E11: Weekly | L11: =IF(F11="","",4*F11-(4*G11+H11)-4*F11*Assumptions!$B$5) | M11: =IF(F11="","",(Assumptions!$B$6+Assumptions!$B$7)*F11-((Assumptions!$B$6+Assumptions!$B$7)*G11+I11)-Assumptions!$B$7*K11-(Assumptions!$B$6+Assumptions!$B$7)*F11*Assumptions!$B$5) | N11: =IF(F11="","",(Assumptions!$B$8+Assumptions!$B$9)*F11-((Assumptions!$B$8+Assumptions!$B$9)*G11+J11)-Assumptions!$B$9*K11-(Assumptions!$B$8+Assumptions!$B$9)*F11*Assumptions!$B$5) | O11: =IF(L11="","",IF(L11<0,"LOSS","OK")) | P11: 4x4: fee by vehicles needed
A12: 8 | B12: Full Day Minya Archaeological Tour | C12: Day tour | D12: Cairo | E12: Weekly / on request | L12: =IF(F12="","",4*F12-(4*G12+H12)-4*F12*Assumptions!$B$5) | M12: =IF(F12="","",(Assumptions!$B$6+Assumptions!$B$7)*F12-((Assumptions!$B$6+Assumptions!$B$7)*G12+I12)-Assumptions!$B$7*K12-(Assumptions!$B$6+Assumptions!$B$7)*F12*Assumptions!$B$5) | N12: =IF(F12="","",(Assumptions!$B$8+Assumptions!$B$9)*F12-((Assumptions!$B$8+Assumptions!$B$9)*G12+J12)-Assumptions!$B$9*K12-(Assumptions!$B$8+Assumptions!$B$9)*F12*Assumptions!$B$5) | O12: =IF(L12="","",IF(L12<0,"LOSS","OK")) | P12: Longest day; lowest likely demand
A13: 9 | B13: Luxor in Depth: East & West Bank Full Day | C13: Day tour | D13: Luxor | E13: Daily | L13: =IF(F13="","",4*F13-(4*G13+H13)-4*F13*Assumptions!$B$5) | M13: =IF(F13="","",(Assumptions!$B$6+Assumptions!$B$7)*F13-((Assumptions!$B$6+Assumptions!$B$7)*G13+I13)-Assumptions!$B$7*K13-(Assumptions!$B$6+Assumptions!$B$7)*F13*Assumptions!$B$5) | N13: =IF(F13="","",(Assumptions!$B$8+Assumptions!$B$9)*F13-((Assumptions!$B$8+Assumptions!$B$9)*G13+J13)-Assumptions!$B$9*K13-(Assumptions!$B$8+Assumptions!$B$9)*F13*Assumptions!$B$5) | O13: =IF(L13="","",IF(L13<0,"LOSS","OK"))
A14: 10 | B14: The Grand West Bank: Tombs, Temples & Deir el-Medina | C14: Day tour | D14: Luxor | E14: 3x weekly | L14: =IF(F14="","",4*F14-(4*G14+H14)-4*F14*Assumptions!$B$5) | M14: =IF(F14="","",(Assumptions!$B$6+Assumptions!$B$7)*F14-((Assumptions!$B$6+Assumptions!$B$7)*G14+I14)-Assumptions!$B$7*K14-(Assumptions!$B$6+Assumptions!$B$7)*F14*Assumptions!$B$5) | N14: =IF(F14="","",(Assumptions!$B$8+Assumptions!$B$9)*F14-((Assumptions!$B$8+Assumptions!$B$9)*G14+J14)-Assumptions!$B$9*K14-(Assumptions!$B$8+Assumptions!$B$9)*F14*Assumptions!$B$5) | O14: =IF(L14="","",IF(L14<0,"LOSS","OK"))
A15: 11 | B15: Dendera & Abydos: the Far Temples North of Luxor | C15: Day tour | D15: Luxor | E15: 2x weekly | L15: =IF(F15="","",4*F15-(4*G15+H15)-4*F15*Assumptions!$B$5) | M15: =IF(F15="","",(Assumptions!$B$6+Assumptions!$B$7)*F15-((Assumptions!$B$6+Assumptions!$B$7)*G15+I15)-Assumptions!$B$7*K15-(Assumptions!$B$6+Assumptions!$B$7)*F15*Assumptions!$B$5) | N15: =IF(F15="","",(Assumptions!$B$8+Assumptions!$B$9)*F15-((Assumptions!$B$8+Assumptions!$B$9)*G15+J15)-Assumptions!$B$9*K15-(Assumptions!$B$8+Assumptions!$B$9)*F15*Assumptions!$B$5) | O15: =IF(L15="","",IF(L15<0,"LOSS","OK"))
A16: 12 | B16: Aswan Highlights: Unfinished Obelisk, High Dam & Philae | C16: Day tour | D16: Aswan | E16: Daily | L16: =IF(F16="","",4*F16-(4*G16+H16)-4*F16*Assumptions!$B$5) | M16: =IF(F16="","",(Assumptions!$B$6+Assumptions!$B$7)*F16-((Assumptions!$B$6+Assumptions!$B$7)*G16+I16)-Assumptions!$B$7*K16-(Assumptions!$B$6+Assumptions!$B$7)*F16*Assumptions!$B$5) | N16: =IF(F16="","",(Assumptions!$B$8+Assumptions!$B$9)*F16-((Assumptions!$B$8+Assumptions!$B$9)*G16+J16)-Assumptions!$B$9*K16-(Assumptions!$B$8+Assumptions!$B$9)*F16*Assumptions!$B$5) | O16: =IF(L16="","",IF(L16<0,"LOSS","OK"))
A17: 13 | B17: Aswan to Abu Simbel: Temples of Ramesses II & Nefertari | C17: Day tour | D17: Aswan | E17: Daily | L17: =IF(F17="","",4*F17-(4*G17+H17)-4*F17*Assumptions!$B$5) | M17: =IF(F17="","",(Assumptions!$B$6+Assumptions!$B$7)*F17-((Assumptions!$B$6+Assumptions!$B$7)*G17+I17)-Assumptions!$B$7*K17-(Assumptions!$B$6+Assumptions!$B$7)*F17*Assumptions!$B$5) | N17: =IF(F17="","",(Assumptions!$B$8+Assumptions!$B$9)*F17-((Assumptions!$B$8+Assumptions!$B$9)*G17+J17)-Assumptions!$B$9*K17-(Assumptions!$B$8+Assumptions!$B$9)*F17*Assumptions!$B$5) | O17: =IF(L17="","",IF(L17<0,"LOSS","OK")) | P17: Title typo fixed
A18: 14 | B18: Luxor to Aswan: Edfu & Kom Ombo Temple Road | C18: One-way road tour | D18: Luxor → Aswan | E18: Merge | L18: =IF(F18="","",4*F18-(4*G18+H18)-4*F18*Assumptions!$B$5) | M18: =IF(F18="","",(Assumptions!$B$6+Assumptions!$B$7)*F18-((Assumptions!$B$6+Assumptions!$B$7)*G18+I18)-Assumptions!$B$7*K18-(Assumptions!$B$6+Assumptions!$B$7)*F18*Assumptions!$B$5) | N18: =IF(F18="","",(Assumptions!$B$8+Assumptions!$B$9)*F18-((Assumptions!$B$8+Assumptions!$B$9)*G18+J18)-Assumptions!$B$9*K18-(Assumptions!$B$8+Assumptions!$B$9)*F18*Assumptions!$B$5) | O18: =IF(L18="","",IF(L18<0,"LOSS","OK")) | P18: Near-duplicate of #15
A19: 15 | B19: Luxor to Aswan: Esna, Edfu & Kom Ombo Temple Road | C19: One-way road tour | D19: Luxor → Aswan | E19: 3x weekly | L19: =IF(F19="","",4*F19-(4*G19+H19)-4*F19*Assumptions!$B$5) | M19: =IF(F19="","",(Assumptions!$B$6+Assumptions!$B$7)*F19-((Assumptions!$B$6+Assumptions!$B$7)*G19+I19)-Assumptions!$B$7*K19-(Assumptions!$B$6+Assumptions!$B$7)*F19*Assumptions!$B$5) | N19: =IF(F19="","",(Assumptions!$B$8+Assumptions!$B$9)*F19-((Assumptions!$B$8+Assumptions!$B$9)*G19+J19)-Assumptions!$B$9*K19-(Assumptions!$B$8+Assumptions!$B$9)*F19*Assumptions!$B$5) | O19: =IF(L19="","",IF(L19<0,"LOSS","OK"))
A20: 16 | B20: Kom Ombo, Edfu & Esna: Downriver from Aswan to Luxor | C20: One-way road tour | D20: Aswan → Luxor | E20: 3x weekly | L20: =IF(F20="","",4*F20-(4*G20+H20)-4*F20*Assumptions!$B$5) | M20: =IF(F20="","",(Assumptions!$B$6+Assumptions!$B$7)*F20-((Assumptions!$B$6+Assumptions!$B$7)*G20+I20)-Assumptions!$B$7*K20-(Assumptions!$B$6+Assumptions!$B$7)*F20*Assumptions!$B$5) | N20: =IF(F20="","",(Assumptions!$B$8+Assumptions!$B$9)*F20-((Assumptions!$B$8+Assumptions!$B$9)*G20+J20)-Assumptions!$B$9*K20-(Assumptions!$B$8+Assumptions!$B$9)*F20*Assumptions!$B$5) | O20: =IF(L20="","",IF(L20<0,"LOSS","OK"))

Sheet Cruises & multi-day
A1: Cruises and multi-day tours
A3: # | B3: Product | C3: Type | D3: Departure pattern | E3: GoAhead deadline (days before) | F3: Retail per person (twin share) | G3: Land services per traveller | H3: Room/cabin per trip: twin (per room) | I3: Room/cabin per trip: single (per room) | J3: Departure fee 4–6 | K3: Departure fee 7–9 | L3: Departure fee 10–12 | M3: Agency commission per seat | N3: Sawa margin A: 4 direct, 2 twin rooms | O3: Sawa margin B: 4 direct, 1 twin + 2 singles | P3: Cost of single promise | Q3: Loss at 4? | R3: Notes
A4: EX | B4: EXAMPLE (illustrative numbers) | C4: Cruise | D4: Ship sailing days | E4: 21 | F4: 900 | G4: 180 | H4: 700 | I4: 600 | J4: 120 | K4: 160 | L4: 200 | M4: 60 | N4: =IF(F4="","",4*F4-(4*G4+2*H4+J4)-4*F4*Assumptions!$B$5) -> 1252 | O4: =IF(F4="","",4*F4-(4*G4+1*H4+2*I4+J4)-4*F4*Assumptions!$B$5) -> 752 | P4: =IF(F4="","",N4-O4) -> 500 | Q4: =IF(N4="","",IF(O4<0,"LOSS if solos unpaired",IF(N4<0,"LOSS","OK"))) -> OK | R4: Illustrative only; not a real rate
A5: 17 | B5: Nile Discovery: 4-Day Cruise from Aswan to Luxor | C5: Cruise | D5: Ship sailing days | N5: =IF(F5="","",4*F5-(4*G5+2*H5+J5)-4*F5*Assumptions!$B$5) | O5: =IF(F5="","",4*F5-(4*G5+1*H5+2*I5+J5)-4*F5*Assumptions!$B$5) | P5: =IF(F5="","",N5-O5) | Q5: =IF(N5="","",IF(O5<0,"LOSS if solos unpaired",IF(N5<0,"LOSS","OK")))
A6: 18 | B6: Nile Majesty: 5-Day River Cruise from Luxor | C6: Cruise | D6: Ship sailing days | N6: =IF(F6="","",4*F6-(4*G6+2*H6+J6)-4*F6*Assumptions!$B$5) | O6: =IF(F6="","",4*F6-(4*G6+1*H6+2*I6+J6)-4*F6*Assumptions!$B$5) | P6: =IF(F6="","",N6-O6) | Q6: =IF(N6="","",IF(O6<0,"LOSS if solos unpaired",IF(N6<0,"LOSS","OK")))
A7: 19 | B7: Cairo and Luxor 4-Day Discovery | C7: Multi-day | D7: Weekly | N7: =IF(F7="","",4*F7-(4*G7+2*H7+J7)-4*F7*Assumptions!$B$5) | O7: =IF(F7="","",4*F7-(4*G7+1*H7+2*I7+J7)-4*F7*Assumptions!$B$5) | P7: =IF(F7="","",N7-O7) | Q7: =IF(N7="","",IF(O7<0,"LOSS if solos unpaired",IF(N7<0,"LOSS","OK")))
A8: 20 | B8: Egypt in Depth: 9-Day Nile Cruise & Cairo | C8: Multi-day | D8: Fortnightly | N8: =IF(F8="","",4*F8-(4*G8+2*H8+J8)-4*F8*Assumptions!$B$5) | O8: =IF(F8="","",4*F8-(4*G8+1*H8+2*I8+J8)-4*F8*Assumptions!$B$5) | P8: =IF(F8="","",N8-O8) | Q8: =IF(N8="","",IF(O8<0,"LOSS if solos unpaired",IF(N8<0,"LOSS","OK")))
A9: 21 | B9: Egypt End to End: Cairo, Nile Cruise & Hurghada, 12 Days | C9: Multi-day | D9: Fortnightly | N9: =IF(F9="","",4*F9-(4*G9+2*H9+J9)-4*F9*Assumptions!$B$5) | O9: =IF(F9="","",4*F9-(4*G9+1*H9+2*I9+J9)-4*F9*Assumptions!$B$5) | P9: =IF(F9="","",N9-O9) | Q9: =IF(N9="","",IF(O9<0,"LOSS if solos unpaired",IF(N9<0,"LOSS","OK"))) | R9: Beach nights: solo pairing hardest here

Sheet Roster
A1: Roster template (Schedule 3)
A2: Enter the operator code for each product and weekday. Leave blank if the product does not run that day.
A4: # | B4: Product | C4: Mon | D4: Tue | E4: Wed | F4: Thu | G4: Fri | H4: Sat | I4: Sun
A5: 1 | B5: Giza Pyramids, Sphinx & the Grand Egyptian Museum
A6: 2 | B6: Giza Uncovered: Pyramids, Sphinx & Stories
A7: 3 | B7: Secrets of the Grand Egyptian Museum
A8: 4 | B8: Memphis, Saqqara & Dahshur: Birth of the Pyramid
A9: 5 | B9: Cairo to Alexandria: the Mediterranean Day Tour
A10: 6 | B10: Fayoum Oasis, Meidum & Hawara Pyramids
A11: 7 | B11: Whale Valley & Wadi El Rayan: Fayoum Desert Safari
A12: 8 | B12: Full Day Minya Archaeological Tour
A13: 9 | B13: Luxor in Depth: East & West Bank Full Day
A14: 10 | B14: The Grand West Bank: Tombs, Temples & Deir el-Medina
A15: 11 | B15: Dendera & Abydos: the Far Temples North of Luxor
A16: 12 | B16: Aswan Highlights: Unfinished Obelisk, High Dam & Philae
... A25: 21 | B25: Egypt End to End: Cairo, Nile Cruise & Hurghada, 12 Days
